django_quick/__init__.py
examples/__init__.py
tests/__init__.py
django_quick-0.0.0.dist-info/LICENSE
django_quick-0.0.0.dist-info/METADATA
django_quick-0.0.0.dist-info/WHEEL
django_quick-0.0.0.dist-info/top_level.txt
django_quick-0.0.0.dist-info/RECORD
